[{"name":"abstract fun deserializeAddedMemberToGroup(data: Array<Byte>): AddedMemberToGroup","description":"io.github.positionpal.EventSerializer.deserializeAddedMemberToGroup","location":"kernel-presentation/io.github.positionpal/-event-serializer/deserialize-added-member-to-group.html","searchKeys":["deserializeAddedMemberToGroup","abstract fun deserializeAddedMemberToGroup(data: Array<Byte>): AddedMemberToGroup","io.github.positionpal.EventSerializer.deserializeAddedMemberToGroup"]},{"name":"abstract fun deserializeGroupCreated(data: Array<Byte>): GroupCreated","description":"io.github.positionpal.EventSerializer.deserializeGroupCreated","location":"kernel-presentation/io.github.positionpal/-event-serializer/deserialize-group-created.html","searchKeys":["deserializeGroupCreated","abstract fun deserializeGroupCreated(data: Array<Byte>): GroupCreated","io.github.positionpal.EventSerializer.deserializeGroupCreated"]},{"name":"abstract fun deserializeGroupDeleted(data: Array<Byte>): GroupDeleted","description":"io.github.positionpal.EventSerializer.deserializeGroupDeleted","location":"kernel-presentation/io.github.positionpal/-event-serializer/deserialize-group-deleted.html","searchKeys":["deserializeGroupDeleted","abstract fun deserializeGroupDeleted(data: Array<Byte>): GroupDeleted","io.github.positionpal.EventSerializer.deserializeGroupDeleted"]},{"name":"abstract fun deserializeRemovedMemberToGroup(data: Array<Byte>): RemovedMemberToGroup","description":"io.github.positionpal.EventSerializer.deserializeRemovedMemberToGroup","location":"kernel-presentation/io.github.positionpal/-event-serializer/deserialize-removed-member-to-group.html","searchKeys":["deserializeRemovedMemberToGroup","abstract fun deserializeRemovedMemberToGroup(data: Array<Byte>): RemovedMemberToGroup","io.github.positionpal.EventSerializer.deserializeRemovedMemberToGroup"]},{"name":"abstract fun deserializeUser(data: Array<Byte>): User","description":"io.github.positionpal.EventSerializer.deserializeUser","location":"kernel-presentation/io.github.positionpal/-event-serializer/deserialize-user.html","searchKeys":["deserializeUser","abstract fun deserializeUser(data: Array<Byte>): User","io.github.positionpal.EventSerializer.deserializeUser"]},{"name":"abstract fun serializeAddedMemberToGroup(event: AddedMemberToGroup): Array<Byte>","description":"io.github.positionpal.EventSerializer.serializeAddedMemberToGroup","location":"kernel-presentation/io.github.positionpal/-event-serializer/serialize-added-member-to-group.html","searchKeys":["serializeAddedMemberToGroup","abstract fun serializeAddedMemberToGroup(event: AddedMemberToGroup): Array<Byte>","io.github.positionpal.EventSerializer.serializeAddedMemberToGroup"]},{"name":"abstract fun serializeGroupCreated(event: GroupCreated): Array<Byte>","description":"io.github.positionpal.EventSerializer.serializeGroupCreated","location":"kernel-presentation/io.github.positionpal/-event-serializer/serialize-group-created.html","searchKeys":["serializeGroupCreated","abstract fun serializeGroupCreated(event: GroupCreated): Array<Byte>","io.github.positionpal.EventSerializer.serializeGroupCreated"]},{"name":"abstract fun serializeGroupDeleted(event: GroupDeleted): Array<Byte>","description":"io.github.positionpal.EventSerializer.serializeGroupDeleted","location":"kernel-presentation/io.github.positionpal/-event-serializer/serialize-group-deleted.html","searchKeys":["serializeGroupDeleted","abstract fun serializeGroupDeleted(event: GroupDeleted): Array<Byte>","io.github.positionpal.EventSerializer.serializeGroupDeleted"]},{"name":"abstract fun serializeRemovedMemberToGroup(event: RemovedMemberToGroup): Array<Byte>","description":"io.github.positionpal.EventSerializer.serializeRemovedMemberToGroup","location":"kernel-presentation/io.github.positionpal/-event-serializer/serialize-removed-member-to-group.html","searchKeys":["serializeRemovedMemberToGroup","abstract fun serializeRemovedMemberToGroup(event: RemovedMemberToGroup): Array<Byte>","io.github.positionpal.EventSerializer.serializeRemovedMemberToGroup"]},{"name":"abstract fun serializeUser(user: User): Array<Byte>","description":"io.github.positionpal.EventSerializer.serializeUser","location":"kernel-presentation/io.github.positionpal/-event-serializer/serialize-user.html","searchKeys":["serializeUser","abstract fun serializeUser(user: User): Array<Byte>","io.github.positionpal.EventSerializer.serializeUser"]},{"name":"class AvroConverter","description":"io.github.positionpal.AvroConverter","location":"kernel-presentation/io.github.positionpal/-avro-converter/index.html","searchKeys":["AvroConverter","class AvroConverter","io.github.positionpal.AvroConverter"]},{"name":"constructor()","description":"io.github.positionpal.AvroSerializer.AvroSerializer","location":"kernel-presentation/io.github.positionpal/-avro-serializer/-avro-serializer.html","searchKeys":["AvroSerializer","constructor()","io.github.positionpal.AvroSerializer.AvroSerializer"]},{"name":"interface EventSerializer","description":"io.github.positionpal.EventSerializer","location":"kernel-presentation/io.github.positionpal/-event-serializer/index.html","searchKeys":["EventSerializer","interface EventSerializer","io.github.positionpal.EventSerializer"]},{"name":"open class AvroSerializer : EventSerializer","description":"io.github.positionpal.AvroSerializer","location":"kernel-presentation/io.github.positionpal/-avro-serializer/index.html","searchKeys":["AvroSerializer","open class AvroSerializer : EventSerializer","io.github.positionpal.AvroSerializer"]},{"name":"open fun deserializeAddedMemberToGroup(data: Array<Byte>): AddedMemberToGroup","description":"io.github.positionpal.AvroSerializer.deserializeAddedMemberToGroup","location":"kernel-presentation/io.github.positionpal/-avro-serializer/deserialize-added-member-to-group.html","searchKeys":["deserializeAddedMemberToGroup","open fun deserializeAddedMemberToGroup(data: Array<Byte>): AddedMemberToGroup","io.github.positionpal.AvroSerializer.deserializeAddedMemberToGroup"]},{"name":"open fun deserializeGroupCreated(data: Array<Byte>): GroupCreated","description":"io.github.positionpal.AvroSerializer.deserializeGroupCreated","location":"kernel-presentation/io.github.positionpal/-avro-serializer/deserialize-group-created.html","searchKeys":["deserializeGroupCreated","open fun deserializeGroupCreated(data: Array<Byte>): GroupCreated","io.github.positionpal.AvroSerializer.deserializeGroupCreated"]},{"name":"open fun deserializeGroupDeleted(data: Array<Byte>): GroupDeleted","description":"io.github.positionpal.AvroSerializer.deserializeGroupDeleted","location":"kernel-presentation/io.github.positionpal/-avro-serializer/deserialize-group-deleted.html","searchKeys":["deserializeGroupDeleted","open fun deserializeGroupDeleted(data: Array<Byte>): GroupDeleted","io.github.positionpal.AvroSerializer.deserializeGroupDeleted"]},{"name":"open fun deserializeRemovedMemberToGroup(data: Array<Byte>): RemovedMemberToGroup","description":"io.github.positionpal.AvroSerializer.deserializeRemovedMemberToGroup","location":"kernel-presentation/io.github.positionpal/-avro-serializer/deserialize-removed-member-to-group.html","searchKeys":["deserializeRemovedMemberToGroup","open fun deserializeRemovedMemberToGroup(data: Array<Byte>): RemovedMemberToGroup","io.github.positionpal.AvroSerializer.deserializeRemovedMemberToGroup"]},{"name":"open fun deserializeUser(data: Array<Byte>): User","description":"io.github.positionpal.AvroSerializer.deserializeUser","location":"kernel-presentation/io.github.positionpal/-avro-serializer/deserialize-user.html","searchKeys":["deserializeUser","open fun deserializeUser(data: Array<Byte>): User","io.github.positionpal.AvroSerializer.deserializeUser"]},{"name":"open fun serializeAddedMemberToGroup(event: AddedMemberToGroup): Array<Byte>","description":"io.github.positionpal.AvroSerializer.serializeAddedMemberToGroup","location":"kernel-presentation/io.github.positionpal/-avro-serializer/serialize-added-member-to-group.html","searchKeys":["serializeAddedMemberToGroup","open fun serializeAddedMemberToGroup(event: AddedMemberToGroup): Array<Byte>","io.github.positionpal.AvroSerializer.serializeAddedMemberToGroup"]},{"name":"open fun serializeGroupCreated(event: GroupCreated): Array<Byte>","description":"io.github.positionpal.AvroSerializer.serializeGroupCreated","location":"kernel-presentation/io.github.positionpal/-avro-serializer/serialize-group-created.html","searchKeys":["serializeGroupCreated","open fun serializeGroupCreated(event: GroupCreated): Array<Byte>","io.github.positionpal.AvroSerializer.serializeGroupCreated"]},{"name":"open fun serializeGroupDeleted(event: GroupDeleted): Array<Byte>","description":"io.github.positionpal.AvroSerializer.serializeGroupDeleted","location":"kernel-presentation/io.github.positionpal/-avro-serializer/serialize-group-deleted.html","searchKeys":["serializeGroupDeleted","open fun serializeGroupDeleted(event: GroupDeleted): Array<Byte>","io.github.positionpal.AvroSerializer.serializeGroupDeleted"]},{"name":"open fun serializeRemovedMemberToGroup(event: RemovedMemberToGroup): Array<Byte>","description":"io.github.positionpal.AvroSerializer.serializeRemovedMemberToGroup","location":"kernel-presentation/io.github.positionpal/-avro-serializer/serialize-removed-member-to-group.html","searchKeys":["serializeRemovedMemberToGroup","open fun serializeRemovedMemberToGroup(event: RemovedMemberToGroup): Array<Byte>","io.github.positionpal.AvroSerializer.serializeRemovedMemberToGroup"]},{"name":"open fun serializeUser(user: User): Array<Byte>","description":"io.github.positionpal.AvroSerializer.serializeUser","location":"kernel-presentation/io.github.positionpal/-avro-serializer/serialize-user.html","searchKeys":["serializeUser","open fun serializeUser(user: User): Array<Byte>","io.github.positionpal.AvroSerializer.serializeUser"]},{"name":"open fun toAddedMemberToGroup(avroAddedMemberToGroup: AddedMemberToGroupEvent): AddedMemberToGroup","description":"io.github.positionpal.AvroConverter.toAddedMemberToGroup","location":"kernel-presentation/io.github.positionpal/-avro-converter/to-added-member-to-group.html","searchKeys":["toAddedMemberToGroup","open fun toAddedMemberToGroup(avroAddedMemberToGroup: AddedMemberToGroupEvent): AddedMemberToGroup","io.github.positionpal.AvroConverter.toAddedMemberToGroup"]},{"name":"open fun toAvroAddedMemberToGroup(addedMemberToGroup: AddedMemberToGroup): AddedMemberToGroupEvent","description":"io.github.positionpal.AvroConverter.toAvroAddedMemberToGroup","location":"kernel-presentation/io.github.positionpal/-avro-converter/to-avro-added-member-to-group.html","searchKeys":["toAvroAddedMemberToGroup","open fun toAvroAddedMemberToGroup(addedMemberToGroup: AddedMemberToGroup): AddedMemberToGroupEvent","io.github.positionpal.AvroConverter.toAvroAddedMemberToGroup"]},{"name":"open fun toAvroGroupCreated(groupCreated: GroupCreated): GroupCreatedEvent","description":"io.github.positionpal.AvroConverter.toAvroGroupCreated","location":"kernel-presentation/io.github.positionpal/-avro-converter/to-avro-group-created.html","searchKeys":["toAvroGroupCreated","open fun toAvroGroupCreated(groupCreated: GroupCreated): GroupCreatedEvent","io.github.positionpal.AvroConverter.toAvroGroupCreated"]},{"name":"open fun toAvroGroupDeleted(groupDeleted: GroupDeleted): GroupDeletedEvent","description":"io.github.positionpal.AvroConverter.toAvroGroupDeleted","location":"kernel-presentation/io.github.positionpal/-avro-converter/to-avro-group-deleted.html","searchKeys":["toAvroGroupDeleted","open fun toAvroGroupDeleted(groupDeleted: GroupDeleted): GroupDeletedEvent","io.github.positionpal.AvroConverter.toAvroGroupDeleted"]},{"name":"open fun toAvroRemovedMemberToGroup(removedMemberToGroup: RemovedMemberToGroup): RemovedMemberToGroupEvent","description":"io.github.positionpal.AvroConverter.toAvroRemovedMemberToGroup","location":"kernel-presentation/io.github.positionpal/-avro-converter/to-avro-removed-member-to-group.html","searchKeys":["toAvroRemovedMemberToGroup","open fun toAvroRemovedMemberToGroup(removedMemberToGroup: RemovedMemberToGroup): RemovedMemberToGroupEvent","io.github.positionpal.AvroConverter.toAvroRemovedMemberToGroup"]},{"name":"open fun toAvroUser(user: User): AvroUser","description":"io.github.positionpal.AvroConverter.toAvroUser","location":"kernel-presentation/io.github.positionpal/-avro-converter/to-avro-user.html","searchKeys":["toAvroUser","open fun toAvroUser(user: User): AvroUser","io.github.positionpal.AvroConverter.toAvroUser"]},{"name":"open fun toGroupCreated(avroGroupCreated: GroupCreatedEvent): GroupCreated","description":"io.github.positionpal.AvroConverter.toGroupCreated","location":"kernel-presentation/io.github.positionpal/-avro-converter/to-group-created.html","searchKeys":["toGroupCreated","open fun toGroupCreated(avroGroupCreated: GroupCreatedEvent): GroupCreated","io.github.positionpal.AvroConverter.toGroupCreated"]},{"name":"open fun toGroupDeleted(avroGroupDeleted: GroupDeletedEvent): GroupDeleted","description":"io.github.positionpal.AvroConverter.toGroupDeleted","location":"kernel-presentation/io.github.positionpal/-avro-converter/to-group-deleted.html","searchKeys":["toGroupDeleted","open fun toGroupDeleted(avroGroupDeleted: GroupDeletedEvent): GroupDeleted","io.github.positionpal.AvroConverter.toGroupDeleted"]},{"name":"open fun toRemovedMemberToGroup(avroRemovedMemberToGroup: RemovedMemberToGroupEvent): RemovedMemberToGroup","description":"io.github.positionpal.AvroConverter.toRemovedMemberToGroup","location":"kernel-presentation/io.github.positionpal/-avro-converter/to-removed-member-to-group.html","searchKeys":["toRemovedMemberToGroup","open fun toRemovedMemberToGroup(avroRemovedMemberToGroup: RemovedMemberToGroupEvent): RemovedMemberToGroup","io.github.positionpal.AvroConverter.toRemovedMemberToGroup"]},{"name":"open fun toUser(avroUser: AvroUser): User","description":"io.github.positionpal.AvroConverter.toUser","location":"kernel-presentation/io.github.positionpal/-avro-converter/to-user.html","searchKeys":["toUser","open fun toUser(avroUser: AvroUser): User","io.github.positionpal.AvroConverter.toUser"]},{"name":"GROUP_CREATED","description":"io.github.positionpal.MessageType.GROUP_CREATED","location":"kernel-domain/io.github.positionpal/-message-type/-g-r-o-u-p_-c-r-e-a-t-e-d/index.html","searchKeys":["GROUP_CREATED","GROUP_CREATED","io.github.positionpal.MessageType.GROUP_CREATED"]},{"name":"GROUP_DELETED","description":"io.github.positionpal.MessageType.GROUP_DELETED","location":"kernel-domain/io.github.positionpal/-message-type/-g-r-o-u-p_-d-e-l-e-t-e-d/index.html","searchKeys":["GROUP_DELETED","GROUP_DELETED","io.github.positionpal.MessageType.GROUP_DELETED"]},{"name":"MEMBER_ADDED","description":"io.github.positionpal.MessageType.MEMBER_ADDED","location":"kernel-domain/io.github.positionpal/-message-type/-m-e-m-b-e-r_-a-d-d-e-d/index.html","searchKeys":["MEMBER_ADDED","MEMBER_ADDED","io.github.positionpal.MessageType.MEMBER_ADDED"]},{"name":"MEMBER_REMOVED","description":"io.github.positionpal.MessageType.MEMBER_REMOVED","location":"kernel-domain/io.github.positionpal/-message-type/-m-e-m-b-e-r_-r-e-m-o-v-e-d/index.html","searchKeys":["MEMBER_REMOVED","MEMBER_REMOVED","io.github.positionpal.MessageType.MEMBER_REMOVED"]},{"name":"USER_CREATED","description":"io.github.positionpal.MessageType.USER_CREATED","location":"kernel-domain/io.github.positionpal/-message-type/-u-s-e-r_-c-r-e-a-t-e-d/index.html","searchKeys":["USER_CREATED","USER_CREATED","io.github.positionpal.MessageType.USER_CREATED"]},{"name":"USER_DELETED","description":"io.github.positionpal.MessageType.USER_DELETED","location":"kernel-domain/io.github.positionpal/-message-type/-u-s-e-r_-d-e-l-e-t-e-d/index.html","searchKeys":["USER_DELETED","USER_DELETED","io.github.positionpal.MessageType.USER_DELETED"]},{"name":"abstract fun addedMember(): User","description":"io.github.positionpal.AddedMemberToGroup.addedMember","location":"kernel-domain/io.github.positionpal/-added-member-to-group/added-member.html","searchKeys":["addedMember","abstract fun addedMember(): User","io.github.positionpal.AddedMemberToGroup.addedMember"]},{"name":"abstract fun createdBy(): User","description":"io.github.positionpal.GroupCreated.createdBy","location":"kernel-domain/io.github.positionpal/-group-created/created-by.html","searchKeys":["createdBy","abstract fun createdBy(): User","io.github.positionpal.GroupCreated.createdBy"]},{"name":"abstract fun email(): String","description":"io.github.positionpal.User.email","location":"kernel-domain/io.github.positionpal/-user/email.html","searchKeys":["email","abstract fun email(): String","io.github.positionpal.User.email"]},{"name":"abstract fun groupId(): String","description":"io.github.positionpal.AddedMemberToGroup.groupId","location":"kernel-domain/io.github.positionpal/-added-member-to-group/group-id.html","searchKeys":["groupId","abstract fun groupId(): String","io.github.positionpal.AddedMemberToGroup.groupId"]},{"name":"abstract fun groupId(): String","description":"io.github.positionpal.GroupCreated.groupId","location":"kernel-domain/io.github.positionpal/-group-created/group-id.html","searchKeys":["groupId","abstract fun groupId(): String","io.github.positionpal.GroupCreated.groupId"]},{"name":"abstract fun groupId(): String","description":"io.github.positionpal.GroupDeleted.groupId","location":"kernel-domain/io.github.positionpal/-group-deleted/group-id.html","searchKeys":["groupId","abstract fun groupId(): String","io.github.positionpal.GroupDeleted.groupId"]},{"name":"abstract fun groupId(): String","description":"io.github.positionpal.RemovedMemberToGroup.groupId","location":"kernel-domain/io.github.positionpal/-removed-member-to-group/group-id.html","searchKeys":["groupId","abstract fun groupId(): String","io.github.positionpal.RemovedMemberToGroup.groupId"]},{"name":"abstract fun id(): String","description":"io.github.positionpal.User.id","location":"kernel-domain/io.github.positionpal/-user/id.html","searchKeys":["id","abstract fun id(): String","io.github.positionpal.User.id"]},{"name":"abstract fun name(): String","description":"io.github.positionpal.User.name","location":"kernel-domain/io.github.positionpal/-user/name.html","searchKeys":["name","abstract fun name(): String","io.github.positionpal.User.name"]},{"name":"abstract fun removedMember(): User","description":"io.github.positionpal.RemovedMemberToGroup.removedMember","location":"kernel-domain/io.github.positionpal/-removed-member-to-group/removed-member.html","searchKeys":["removedMember","abstract fun removedMember(): User","io.github.positionpal.RemovedMemberToGroup.removedMember"]},{"name":"abstract fun role(): String","description":"io.github.positionpal.User.role","location":"kernel-domain/io.github.positionpal/-user/role.html","searchKeys":["role","abstract fun role(): String","io.github.positionpal.User.role"]},{"name":"abstract fun surname(): String","description":"io.github.positionpal.User.surname","location":"kernel-domain/io.github.positionpal/-user/surname.html","searchKeys":["surname","abstract fun surname(): String","io.github.positionpal.User.surname"]},{"name":"class AddedMemberToGroupImpl : Record, AddedMemberToGroup","description":"io.github.positionpal.AddedMemberToGroupImpl","location":"kernel-domain/io.github.positionpal/-added-member-to-group-impl/index.html","searchKeys":["AddedMemberToGroupImpl","class AddedMemberToGroupImpl : Record, AddedMemberToGroup","io.github.positionpal.AddedMemberToGroupImpl"]},{"name":"class GroupCreatedImpl : Record, GroupCreated","description":"io.github.positionpal.GroupCreatedImpl","location":"kernel-domain/io.github.positionpal/-group-created-impl/index.html","searchKeys":["GroupCreatedImpl","class GroupCreatedImpl : Record, GroupCreated","io.github.positionpal.GroupCreatedImpl"]},{"name":"class GroupDeletedImpl : Record, GroupDeleted","description":"io.github.positionpal.GroupDeletedImpl","location":"kernel-domain/io.github.positionpal/-group-deleted-impl/index.html","searchKeys":["GroupDeletedImpl","class GroupDeletedImpl : Record, GroupDeleted","io.github.positionpal.GroupDeletedImpl"]},{"name":"class RemovedMemberToGroupImpl : Record, RemovedMemberToGroup","description":"io.github.positionpal.RemovedMemberToGroupImpl","location":"kernel-domain/io.github.positionpal/-removed-member-to-group-impl/index.html","searchKeys":["RemovedMemberToGroupImpl","class RemovedMemberToGroupImpl : Record, RemovedMemberToGroup","io.github.positionpal.RemovedMemberToGroupImpl"]},{"name":"class UserImpl : Record, User","description":"io.github.positionpal.UserImpl","location":"kernel-domain/io.github.positionpal/-user-impl/index.html","searchKeys":["UserImpl","class UserImpl : Record, User","io.github.positionpal.UserImpl"]},{"name":"constructor()","description":"io.github.positionpal.AddedMemberToGroupImpl.AddedMemberToGroupImpl","location":"kernel-domain/io.github.positionpal/-added-member-to-group-impl/-added-member-to-group-impl.html","searchKeys":["AddedMemberToGroupImpl","constructor()","io.github.positionpal.AddedMemberToGroupImpl.AddedMemberToGroupImpl"]},{"name":"constructor()","description":"io.github.positionpal.GroupCreatedImpl.GroupCreatedImpl","location":"kernel-domain/io.github.positionpal/-group-created-impl/-group-created-impl.html","searchKeys":["GroupCreatedImpl","constructor()","io.github.positionpal.GroupCreatedImpl.GroupCreatedImpl"]},{"name":"constructor()","description":"io.github.positionpal.GroupDeletedImpl.GroupDeletedImpl","location":"kernel-domain/io.github.positionpal/-group-deleted-impl/-group-deleted-impl.html","searchKeys":["GroupDeletedImpl","constructor()","io.github.positionpal.GroupDeletedImpl.GroupDeletedImpl"]},{"name":"constructor()","description":"io.github.positionpal.RemovedMemberToGroupImpl.RemovedMemberToGroupImpl","location":"kernel-domain/io.github.positionpal/-removed-member-to-group-impl/-removed-member-to-group-impl.html","searchKeys":["RemovedMemberToGroupImpl","constructor()","io.github.positionpal.RemovedMemberToGroupImpl.RemovedMemberToGroupImpl"]},{"name":"constructor()","description":"io.github.positionpal.UserImpl.UserImpl","location":"kernel-domain/io.github.positionpal/-user-impl/-user-impl.html","searchKeys":["UserImpl","constructor()","io.github.positionpal.UserImpl.UserImpl"]},{"name":"constructor(type: MessageType, data: Array<Byte>)","description":"io.github.positionpal.Message.Message","location":"kernel-domain/io.github.positionpal/-message/-message.html","searchKeys":["Message","constructor(type: MessageType, data: Array<Byte>)","io.github.positionpal.Message.Message"]},{"name":"enum MessageType","description":"io.github.positionpal.MessageType","location":"kernel-domain/io.github.positionpal/-message-type/index.html","searchKeys":["MessageType","enum MessageType","io.github.positionpal.MessageType"]},{"name":"interface AddedMemberToGroup","description":"io.github.positionpal.AddedMemberToGroup","location":"kernel-domain/io.github.positionpal/-added-member-to-group/index.html","searchKeys":["AddedMemberToGroup","interface AddedMemberToGroup","io.github.positionpal.AddedMemberToGroup"]},{"name":"interface GroupCreated","description":"io.github.positionpal.GroupCreated","location":"kernel-domain/io.github.positionpal/-group-created/index.html","searchKeys":["GroupCreated","interface GroupCreated","io.github.positionpal.GroupCreated"]},{"name":"interface GroupDeleted","description":"io.github.positionpal.GroupDeleted","location":"kernel-domain/io.github.positionpal/-group-deleted/index.html","searchKeys":["GroupDeleted","interface GroupDeleted","io.github.positionpal.GroupDeleted"]},{"name":"interface RemovedMemberToGroup","description":"io.github.positionpal.RemovedMemberToGroup","location":"kernel-domain/io.github.positionpal/-removed-member-to-group/index.html","searchKeys":["RemovedMemberToGroup","interface RemovedMemberToGroup","io.github.positionpal.RemovedMemberToGroup"]},{"name":"interface User","description":"io.github.positionpal.User","location":"kernel-domain/io.github.positionpal/-user/index.html","searchKeys":["User","interface User","io.github.positionpal.User"]},{"name":"open class Message","description":"io.github.positionpal.Message","location":"kernel-domain/io.github.positionpal/-message/index.html","searchKeys":["Message","open class Message","io.github.positionpal.Message"]},{"name":"open fun create(groupId: String): GroupDeleted","description":"io.github.positionpal.GroupDeleted.create","location":"kernel-domain/io.github.positionpal/-group-deleted/create.html","searchKeys":["create","open fun create(groupId: String): GroupDeleted","io.github.positionpal.GroupDeleted.create"]},{"name":"open fun create(groupId: String, addedMember: User): AddedMemberToGroup","description":"io.github.positionpal.AddedMemberToGroup.create","location":"kernel-domain/io.github.positionpal/-added-member-to-group/create.html","searchKeys":["create","open fun create(groupId: String, addedMember: User): AddedMemberToGroup","io.github.positionpal.AddedMemberToGroup.create"]},{"name":"open fun create(groupId: String, createdBy: User): GroupCreated","description":"io.github.positionpal.GroupCreated.create","location":"kernel-domain/io.github.positionpal/-group-created/create.html","searchKeys":["create","open fun create(groupId: String, createdBy: User): GroupCreated","io.github.positionpal.GroupCreated.create"]},{"name":"open fun create(groupId: String, removedMember: User): RemovedMemberToGroup","description":"io.github.positionpal.RemovedMemberToGroup.create","location":"kernel-domain/io.github.positionpal/-removed-member-to-group/create.html","searchKeys":["create","open fun create(groupId: String, removedMember: User): RemovedMemberToGroup","io.github.positionpal.RemovedMemberToGroup.create"]},{"name":"open fun create(id: String, name: String, surname: String, email: String, role: String): User","description":"io.github.positionpal.User.create","location":"kernel-domain/io.github.positionpal/-user/create.html","searchKeys":["create","open fun create(id: String, name: String, surname: String, email: String, role: String): User","io.github.positionpal.User.create"]},{"name":"open fun valueOf(name: String): MessageType","description":"io.github.positionpal.MessageType.valueOf","location":"kernel-domain/io.github.positionpal/-message-type/value-of.html","searchKeys":["valueOf","open fun valueOf(name: String): MessageType","io.github.positionpal.MessageType.valueOf"]},{"name":"open fun values(): Array<MessageType>","description":"io.github.positionpal.MessageType.values","location":"kernel-domain/io.github.positionpal/-message-type/values.html","searchKeys":["values","open fun values(): Array<MessageType>","io.github.positionpal.MessageType.values"]},{"name":"val data: Array<Byte>","description":"io.github.positionpal.Message.data","location":"kernel-domain/io.github.positionpal/-message/data.html","searchKeys":["data","val data: Array<Byte>","io.github.positionpal.Message.data"]},{"name":"val type: MessageType","description":"io.github.positionpal.Message.type","location":"kernel-domain/io.github.positionpal/-message/type.html","searchKeys":["type","val type: MessageType","io.github.positionpal.Message.type"]}]